{"_invocation_id": "904a1a03-e641-413a-b372-d1955b3a9c26", "linked": {"0": {"name": "source.datalake.staging.ipv_precios_vivienda", "type": "source", "succ": [1, 2, 3, 4, 6]}, "1": {"name": "model.datalake.dim_comunidad", "type": "model", "succ": [5]}, "2": {"name": "model.datalake.dim_indicador", "type": "model", "succ": [5]}, "3": {"name": "model.datalake.dim_tiempo", "type": "model", "succ": [5]}, "4": {"name": "model.datalake.dim_tipo_vivienda", "type": "model", "succ": [5]}, "5": {"name": "model.datalake.fct_precios_vivienda", "type": "model"}, "6": {"name": "model.datalake.stg_ipv", "type": "model", "succ": [5]}}}